rda_python_dbms/MyDBI.py
rda_python_dbms/PgDDLLib.py
rda_python_dbms/__init__.py
rda_python_dbms/pg_backup.py
rda_python_dbms/pg_chksum.py
rda_python_dbms/pg_dbdump.py
rda_python_dbms/pg_dbrestore.py
rda_python_dbms/pg_ddl.py
rda_python_dbms/pg_ddllib.py
rda_python_dbms/pg_schema.py
rda_python_dbms/pg_seq.py
rda_python_dbms/pgbackup.py
rda_python_dbms/pgchksum.py
rda_python_dbms/pgcmptables.py
rda_python_dbms/pgdbdump.py
rda_python_dbms/pgdbrestore.py
rda_python_dbms/pgddl.py
rda_python_dbms/pgddl.usg
rda_python_dbms/pgschema.py
rda_python_dbms/pgseq.py
rda_python_dbms/pg_config/pg_hba.conf.source.rda-pgdb-01
rda_python_dbms/pg_config/postgresql.conf.source.rda-pgdb-01
rda_python_dbms/pg_config/postgresql.conf.source.rda-pgdb-02
rda_python_dbms/pg_config/postgresql.conf.source.rda-pgdb-03
rda_python_dbms/tables/cntldb/iattm.json
rda_python_dbms/tables/cntldb/iattm_daily.json
rda_python_dbms/tables/cntldb/iinventory.json
rda_python_dbms/tables/cntldb/inventory.json
rda_python_dbms/tables/cntldb/itidx.json
rda_python_dbms/tables/cntldb/ivadref.json
rda_python_dbms/tables/cntldb1/iattm.json
rda_python_dbms/tables/cntldb1/iattm_daily.json
rda_python_dbms/tables/cntldb1/inventory.json
rda_python_dbms/tables/cntldb1/itidx.json
rda_python_dbms/tables/dssdb/acard.json
rda_python_dbms/tables/dssdb/access_types.json
rda_python_dbms/tables/dssdb/access_types_dev.json
rda_python_dbms/tables/dssdb/allusage.json
rda_python_dbms/tables/dssdb/awsusage.json
rda_python_dbms/tables/dssdb/bfile.json
rda_python_dbms/tables/dssdb/bldusage.json
rda_python_dbms/tables/dssdb/cardhist.json
rda_python_dbms/tables/dssdb/checklimit.json
rda_python_dbms/tables/dssdb/ci_cd.json
rda_python_dbms/tables/dssdb/clranges.json
rda_python_dbms/tables/dssdb/cmd_reg.json
rda_python_dbms/tables/dssdb/codusage.json
rda_python_dbms/tables/dssdb/countries.json
rda_python_dbms/tables/dssdb/country_info.json
rda_python_dbms/tables/dssdb/daphist.json
rda_python_dbms/tables/dssdb/dataset.json
rda_python_dbms-2.0.1.dist-info/licenses/LICENSE
rda_python_dbms-2.0.1.dist-info/METADATA
rda_python_dbms-2.0.1.dist-info/WHEEL
rda_python_dbms-2.0.1.dist-info/entry_points.txt
rda_python_dbms-2.0.1.dist-info/top_level.txt
rda_python_dbms-2.0.1.dist-info/RECORD
